LICENSE
MANIFEST.in
requirements.txt
setup.py
test-requirements.txt
cmonkey/__init__.py
cmonkey.egg-info/PKG-INFO
cmonkey.egg-info/SOURCES.txt
cmonkey.egg-info/dependency_links.txt
cmonkey.egg-info/entry_points.txt
cmonkey.egg-info/not-zip-safe
cmonkey.egg-info/requires.txt
cmonkey.egg-info/top_level.txt
cmonkey/cmd/__init__.py