Metadata-Version: 1.1
Name: cmonkey
Version: 0.1.1
Summary: Simple scripting framework for Apache CloudStack
Home-page: https://github.com/momijiame/cmonkey
Author: momijiame
Author-email: amedama.ginmokusei@gmail.com
License: UNKNOWN
Platform: UNKNOWN
Classifier: Programming Language :: Python :: 2
Classifier: Programming Language :: Python :: 2.6
Classifier: Programming Language :: Python :: 2.7
Classifier: Programming Language :: Python :: 3
Classifier: Programming Language :: Python :: 3.3
Classifier: Development Status :: 3 - Alpha
Classifier: License :: OSI Approved :: Apache Software License
Classifier: Intended Audience :: Developers
Classifier: Natural Language :: Japanese
Classifier: Operating System :: POSIX
